[
    {
        "county": "新北市",
        "city": "板橋區",
        "households": 197594,
        "population": 554973,
        "male": 273720,
        "female": 281253
    },
    {
        "county": "新北市",
        "city": "三重區",
        "households": 142452,
        "population": 390190,
        "male": 194082,
        "female": 196108
    },
    {
        "county": "新北市",
        "city": "中和區",
        "households": 157396,
        "population": 414792,
        "male": 204470,
        "female": 210322
    },
    {
        "county": "新北市",
        "city": "永和區",
        "households": 89977,
        "population": 232372,
        "male": 111437,
        "female": 120935
    },
    {
        "county": "新北市",
        "city": "新莊區",
        "households": 139011,
        "population": 403790,
        "male": 199123,
        "female": 204667
    },
    {
        "county": "新北市",
        "city": "新店區",
        "households": 117913,
        "population": 296472,
        "male": 144723,
        "female": 151749
    },
    {
        "county": "新北市",
        "city": "樹林區",
        "households": 62060,
        "population": 179600,
        "male": 90357,
        "female": 89243
    },
    {
        "county": "新北市",
        "city": "鶯歌區",
        "households": 27961,
        "population": 87598,
        "male": 44207,
        "female": 43391
    },
    {
        "county": "新北市",
        "city": "三峽區",
        "households": 36754,
        "population": 105483,
        "male": 53633,
        "female": 51850
    },
    {
        "county": "新北市",
        "city": "淡水區",
        "households": 59711,
        "population": 146470,
        "male": 71097,
        "female": 75373
    },
    {
        "county": "新北市",
        "city": "汐止區",
        "households": 80318,
        "population": 190513,
        "male": 94391,
        "female": 96122
    },
    {
        "county": "新北市",
        "city": "瑞芳區",
        "households": 15933,
        "population": 42040,
        "male": 21423,
        "female": 20617
    },
    {
        "county": "新北市",
        "city": "土城區",
        "households": 83205,
        "population": 238983,
        "male": 119300,
        "female": 119683
    },
    {
        "county": "新北市",
        "city": "蘆洲區",
        "households": 66411,
        "population": 198236,
        "male": 98022,
        "female": 100214
    },
    {
        "county": "新北市",
        "city": "五股區",
        "households": 27756,
        "population": 80487,
        "male": 40747,
        "female": 39740
    },
    {
        "county": "新北市",
        "city": "泰山區",
        "households": 26520,
        "population": 76966,
        "male": 38592,
        "female": 38374
    },
    {
        "county": "新北市",
        "city": "林口區",
        "households": 32407,
        "population": 86374,
        "male": 42621,
        "female": 43753
    },
    {
        "county": "新北市",
        "city": "深坑區",
        "households": 9067,
        "population": 23503,
        "male": 11839,
        "female": 11664
    },
    {
        "county": "新北市",
        "city": "石碇區",
        "households": 3335,
        "population": 7883,
        "male": 4383,
        "female": 3500
    },
    {
        "county": "新北市",
        "city": "坪林區",
        "households": 2463,
        "population": 6541,
        "male": 3638,
        "female": 2903
    },
    {
        "county": "新北市",
        "city": "三芝區",
        "households": 8961,
        "population": 23351,
        "male": 12045,
        "female": 11306
    },
    {
        "county": "新北市",
        "city": "石門區",
        "households": 4151,
        "population": 12812,
        "male": 6708,
        "female": 6104
    },
    {
        "county": "新北市",
        "city": "八里區",
        "households": 12665,
        "population": 35386,
        "male": 17875,
        "female": 17511
    },
    {
        "county": "新北市",
        "city": "平溪區",
        "households": 2396,
        "population": 5205,
        "male": 2911,
        "female": 2294
    },
    {
        "county": "新北市",
        "city": "雙溪區",
        "households": 3804,
        "population": 9559,
        "male": 5176,
        "female": 4383
    },
    {
        "county": "新北市",
        "city": "貢寮區",
        "households": 4434,
        "population": 13540,
        "male": 6986,
        "female": 6554
    },
    {
        "county": "新北市",
        "city": "金山區",
        "households": 6803,
        "population": 22412,
        "male": 11212,
        "female": 11200
    },
    {
        "county": "新北市",
        "city": "萬里區",
        "households": 7129,
        "population": 22161,
        "male": 11224,
        "female": 10937
    },
    {
        "county": "新北市",
        "city": "烏來區",
        "households": 1733,
        "population": 5903,
        "male": 2978,
        "female": 2925
    },
    {
        "county": "臺北市",
        "city": "松山區",
        "households": 78738,
        "population": 209757,
        "male": 99339,
        "female": 110418
    },
    {
        "county": "臺北市",
        "city": "信義區",
        "households": 86785,
        "population": 226433,
        "male": 108902,
        "female": 117531
    },
    {
        "county": "臺北市",
        "city": "大安區",
        "households": 118011,
        "population": 313237,
        "male": 147295,
        "female": 165942
    },
    {
        "county": "臺北市",
        "city": "中山區",
        "households": 93910,
        "population": 223743,
        "male": 105071,
        "female": 118672
    },
    {
        "county": "臺北市",
        "city": "中正區",
        "households": 63061,
        "population": 161149,
        "male": 77654,
        "female": 83495
    },
    {
        "county": "臺北市",
        "city": "大同區",
        "households": 48415,
        "population": 126405,
        "male": 62177,
        "female": 64228
    },
    {
        "county": "臺北市",
        "city": "萬華區",
        "households": 75172,
        "population": 190568,
        "male": 94731,
        "female": 95837
    },
    {
        "county": "臺北市",
        "city": "文山區",
        "households": 99080,
        "population": 266078,
        "male": 128770,
        "female": 137308
    },
    {
        "county": "臺北市",
        "city": "南港區",
        "households": 42856,
        "population": 115961,
        "male": 56981,
        "female": 58980
    },
    {
        "county": "臺北市",
        "city": "內湖區",
        "households": 99500,
        "population": 275199,
        "male": 132495,
        "female": 142704
    },
    {
        "county": "臺北市",
        "city": "士林區",
        "households": 102389,
        "population": 286717,
        "male": 139162,
        "female": 147555
    },
    {
        "county": "臺北市",
        "city": "北投區",
        "households": 91155,
        "population": 251875,
        "male": 122163,
        "female": 129712
    },
    {
        "county": "臺中市",
        "city": "中區",
        "households": 8226,
        "population": 21662,
        "male": 10727,
        "female": 10935
    },
    {
        "county": "臺中市",
        "city": "東區",
        "households": 26110,
        "population": 73913,
        "male": 37210,
        "female": 36703
    },
    {
        "county": "臺中市",
        "city": "南區",
        "households": 43028,
        "population": 115001,
        "male": 55715,
        "female": 59286
    },
    {
        "county": "臺中市",
        "city": "西區",
        "households": 43775,
        "population": 117220,
        "male": 56218,
        "female": 61002
    },
    {
        "county": "臺中市",
        "city": "北區",
        "households": 56492,
        "population": 147565,
        "male": 71387,
        "female": 76178
    },
    {
        "county": "臺中市",
        "city": "西屯區",
        "households": 74988,
        "population": 209399,
        "male": 101258,
        "female": 108141
    },
    {
        "county": "臺中市",
        "city": "南屯區",
        "households": 54465,
        "population": 155586,
        "male": 75127,
        "female": 80459
    },
    {
        "county": "臺中市",
        "city": "北屯區",
        "households": 85627,
        "population": 249521,
        "male": 121000,
        "female": 128521
    },
    {
        "county": "臺中市",
        "city": "豐原區",
        "households": 50389,
        "population": 165516,
        "male": 82114,
        "female": 83402
    },
    {
        "county": "臺中市",
        "city": "東勢區",
        "households": 17068,
        "population": 52843,
        "male": 27426,
        "female": 25417
    },
    {
        "county": "臺中市",
        "city": "大甲區",
        "households": 21877,
        "population": 78121,
        "male": 39612,
        "female": 38509
    },
    {
        "county": "臺中市",
        "city": "清水區",
        "households": 25257,
        "population": 85618,
        "male": 44157,
        "female": 41461
    },
    {
        "county": "臺中市",
        "city": "沙鹿區",
        "households": 24684,
        "population": 83179,
        "male": 42299,
        "female": 40880
    },
    {
        "county": "臺中市",
        "city": "梧棲區",
        "households": 16209,
        "population": 55514,
        "male": 28134,
        "female": 27380
    },
    {
        "county": "臺中市",
        "city": "后里區",
        "households": 14975,
        "population": 54048,
        "male": 27701,
        "female": 26347
    },
    {
        "county": "臺中市",
        "city": "神岡區",
        "households": 17873,
        "population": 63874,
        "male": 32829,
        "female": 31045
    },
    {
        "county": "臺中市",
        "city": "潭子區",
        "households": 33060,
        "population": 101732,
        "male": 50606,
        "female": 51126
    },
    {
        "county": "臺中市",
        "city": "大雅區",
        "households": 26711,
        "population": 90521,
        "male": 45564,
        "female": 44957
    },
    {
        "county": "臺中市",
        "city": "新社區",
        "households": 7371,
        "population": 25488,
        "male": 13314,
        "female": 12174
    },
    {
        "county": "臺中市",
        "city": "石岡區",
        "households": 4868,
        "population": 15816,
        "male": 8221,
        "female": 7595
    },
    {
        "county": "臺中市",
        "city": "外埔區",
        "households": 8969,
        "population": 31982,
        "male": 16445,
        "female": 15537
    },
    {
        "county": "臺中市",
        "city": "大安區",
        "households": 5312,
        "population": 20088,
        "male": 10552,
        "female": 9536
    },
    {
        "county": "臺中市",
        "city": "烏日區",
        "households": 20975,
        "population": 69160,
        "male": 35015,
        "female": 34145
    },
    {
        "county": "臺中市",
        "city": "大肚區",
        "households": 16038,
        "population": 55726,
        "male": 28593,
        "female": 27133
    },
    {
        "county": "臺中市",
        "city": "龍井區",
        "households": 20980,
        "population": 74564,
        "male": 37884,
        "female": 36680
    },
    {
        "county": "臺中市",
        "city": "霧峰區",
        "households": 18899,
        "population": 63872,
        "male": 32781,
        "female": 31091
    },
    {
        "county": "臺中市",
        "city": "太平區",
        "households": 55540,
        "population": 174145,
        "male": 87315,
        "female": 86830
    },
    {
        "county": "臺中市",
        "city": "大里區",
        "households": 63093,
        "population": 200395,
        "male": 99385,
        "female": 101010
    },
    {
        "county": "臺中市",
        "city": "和平區",
        "households": 4423,
        "population": 10701,
        "male": 5786,
        "female": 4915
    },
    {
        "county": "臺南市",
        "city": "新營區",
        "households": 27557,
        "population": 78442,
        "male": 39048,
        "female": 39394
    },
    {
        "county": "臺南市",
        "city": "鹽水區",
        "households": 10005,
        "population": 26899,
        "male": 14003,
        "female": 12896
    },
    {
        "county": "臺南市",
        "city": "白河區",
        "households": 10967,
        "population": 30996,
        "male": 16231,
        "female": 14765
    },
    {
        "county": "臺南市",
        "city": "柳營區",
        "households": 7804,
        "population": 22455,
        "male": 11760,
        "female": 10695
    },
    {
        "county": "臺南市",
        "city": "後壁區",
        "households": 8842,
        "population": 25596,
        "male": 13330,
        "female": 12266
    },
    {
        "county": "臺南市",
        "city": "東山區",
        "households": 8229,
        "population": 22782,
        "male": 12088,
        "female": 10694
    },
    {
        "county": "臺南市",
        "city": "麻豆區",
        "households": 15149,
        "population": 45601,
        "male": 23271,
        "female": 22330
    },
    {
        "county": "臺南市",
        "city": "下營區",
        "households": 9124,
        "population": 25840,
        "male": 13375,
        "female": 12465
    },
    {
        "county": "臺南市",
        "city": "六甲區",
        "households": 7682,
        "population": 23524,
        "male": 12241,
        "female": 11283
    },
    {
        "county": "臺南市",
        "city": "官田區",
        "households": 7637,
        "population": 21986,
        "male": 11252,
        "female": 10734
    },
    {
        "county": "臺南市",
        "city": "大內區",
        "households": 4040,
        "population": 10691,
        "male": 5699,
        "female": 4992
    },
    {
        "county": "臺南市",
        "city": "佳里區",
        "households": 19550,
        "population": 59196,
        "male": 29398,
        "female": 29798
    },
    {
        "county": "臺南市",
        "city": "學甲區",
        "households": 9579,
        "population": 27602,
        "male": 14132,
        "female": 13470
    },
    {
        "county": "臺南市",
        "city": "西港區",
        "households": 7863,
        "population": 25079,
        "male": 12750,
        "female": 12329
    },
    {
        "county": "臺南市",
        "city": "七股區",
        "households": 8056,
        "population": 24655,
        "male": 12889,
        "female": 11766
    },
    {
        "county": "臺南市",
        "city": "將軍區",
        "households": 7422,
        "population": 21280,
        "male": 10840,
        "female": 10440
    },
    {
        "county": "臺南市",
        "city": "北門區",
        "households": 4391,
        "population": 12252,
        "male": 6235,
        "female": 6017
    },
    {
        "county": "臺南市",
        "city": "新化區",
        "households": 13826,
        "population": 44032,
        "male": 22533,
        "female": 21499
    },
    {
        "county": "臺南市",
        "city": "善化區",
        "households": 14962,
        "population": 43990,
        "male": 22225,
        "female": 21765
    },
    {
        "county": "臺南市",
        "city": "新市區",
        "households": 10951,
        "population": 35005,
        "male": 17596,
        "female": 17409
    },
    {
        "county": "臺南市",
        "city": "安定區",
        "households": 9454,
        "population": 30284,
        "male": 15694,
        "female": 14590
    },
    {
        "county": "臺南市",
        "city": "山上區",
        "households": 2730,
        "population": 7757,
        "male": 4090,
        "female": 3667
    },
    {
        "county": "臺南市",
        "city": "玉井區",
        "households": 5094,
        "population": 15224,
        "male": 7871,
        "female": 7353
    },
    {
        "county": "臺南市",
        "city": "楠西區",
        "households": 3556,
        "population": 10453,
        "male": 5544,
        "female": 4909
    },
    {
        "county": "臺南市",
        "city": "南化區",
        "households": 2825,
        "population": 8804,
        "male": 4818,
        "female": 3986
    },
    {
        "county": "臺南市",
        "city": "左鎮區",
        "households": 1981,
        "population": 5369,
        "male": 2987,
        "female": 2382
    },
    {
        "county": "臺南市",
        "city": "仁德區",
        "households": 25059,
        "population": 70152,
        "male": 35929,
        "female": 34223
    },
    {
        "county": "臺南市",
        "city": "歸仁區",
        "households": 20874,
        "population": 66072,
        "male": 33714,
        "female": 32358
    },
    {
        "county": "臺南市",
        "city": "關廟區",
        "households": 10749,
        "population": 35653,
        "male": 18505,
        "female": 17148
    },
    {
        "county": "臺南市",
        "city": "龍崎區",
        "households": 1591,
        "population": 4324,
        "male": 2338,
        "female": 1986
    },
    {
        "county": "臺南市",
        "city": "永康區",
        "households": 76936,
        "population": 220606,
        "male": 109535,
        "female": 111071
    },
    {
        "county": "臺南市",
        "city": "東區",
        "households": 71345,
        "population": 193645,
        "male": 93494,
        "female": 100151
    },
    {
        "county": "臺南市",
        "city": "南區",
        "households": 43776,
        "population": 126189,
        "male": 63210,
        "female": 62979
    },
    {
        "county": "臺南市",
        "city": "北區",
        "households": 48713,
        "population": 132129,
        "male": 64983,
        "female": 67146
    },
    {
        "county": "臺南市",
        "city": "安南區",
        "households": 55784,
        "population": 179858,
        "male": 91330,
        "female": 88528
    },
    {
        "county": "臺南市",
        "city": "安平區",
        "households": 23652,
        "population": 63557,
        "male": 30427,
        "female": 33130
    },
    {
        "county": "臺南市",
        "city": "中西區",
        "households": 30275,
        "population": 78727,
        "male": 38555,
        "female": 40172
    },
    {
        "county": "高雄市",
        "city": "鹽埕區",
        "households": 11054,
        "population": 26722,
        "male": 13383,
        "female": 13339
    },
    {
        "county": "高雄市",
        "city": "鼓山區",
        "households": 53137,
        "population": 132743,
        "male": 64845,
        "female": 67898
    },
    {
        "county": "高雄市",
        "city": "左營區",
        "households": 74881,
        "population": 193335,
        "male": 94872,
        "female": 98463
    },
    {
        "county": "高雄市",
        "city": "楠梓區",
        "households": 62617,
        "population": 173831,
        "male": 86135,
        "female": 87696
    },
    {
        "county": "高雄市",
        "city": "三民區",
        "households": 132672,
        "population": 352124,
        "male": 172124,
        "female": 180000
    },
    {
        "county": "高雄市",
        "city": "新興區",
        "households": 22821,
        "population": 54395,
        "male": 26366,
        "female": 28029
    },
    {
        "county": "高雄市",
        "city": "前金區",
        "households": 12525,
        "population": 28469,
        "male": 13859,
        "female": 14610
    },
    {
        "county": "高雄市",
        "city": "苓雅區",
        "households": 71985,
        "population": 181720,
        "male": 88279,
        "female": 93441
    },
    {
        "county": "高雄市",
        "city": "前鎮區",
        "households": 76947,
        "population": 197772,
        "male": 98099,
        "female": 99673
    },
    {
        "county": "高雄市",
        "city": "旗津區",
        "households": 10995,
        "population": 29786,
        "male": 15433,
        "female": 14353
    },
    {
        "county": "高雄市",
        "city": "小港區",
        "households": 64227,
        "population": 154717,
        "male": 77622,
        "female": 77095
    },
    {
        "county": "高雄市",
        "city": "鳳山區",
        "households": 129287,
        "population": 344961,
        "male": 171366,
        "female": 173595
    },
    {
        "county": "高雄市",
        "city": "林園區",
        "households": 24589,
        "population": 70440,
        "male": 36074,
        "female": 34366
    },
    {
        "county": "高雄市",
        "city": "大寮區",
        "households": 38937,
        "population": 109169,
        "male": 56618,
        "female": 52551
    },
    {
        "county": "高雄市",
        "city": "大樹區",
        "households": 13139,
        "population": 43646,
        "male": 22534,
        "female": 21112
    },
    {
        "county": "高雄市",
        "city": "大社區",
        "households": 11906,
        "population": 33291,
        "male": 17061,
        "female": 16230
    },
    {
        "county": "高雄市",
        "city": "仁武區",
        "households": 27133,
        "population": 74787,
        "male": 38556,
        "female": 36231
    },
    {
        "county": "高雄市",
        "city": "鳥松區",
        "households": 16899,
        "population": 43166,
        "male": 21874,
        "female": 21292
    },
    {
        "county": "高雄市",
        "city": "岡山區",
        "households": 33612,
        "population": 97364,
        "male": 48764,
        "female": 48600
    },
    {
        "county": "高雄市",
        "city": "橋頭區",
        "households": 12880,
        "population": 36771,
        "male": 18819,
        "female": 17952
    },
    {
        "county": "高雄市",
        "city": "燕巢區",
        "households": 10130,
        "population": 30935,
        "male": 16507,
        "female": 14428
    },
    {
        "county": "高雄市",
        "city": "田寮區",
        "households": 3521,
        "population": 8037,
        "male": 4464,
        "female": 3573
    },
    {
        "county": "高雄市",
        "city": "阿蓮區",
        "households": 9225,
        "population": 30193,
        "male": 15223,
        "female": 14970
    },
    {
        "county": "高雄市",
        "city": "路竹區",
        "households": 16175,
        "population": 53496,
        "male": 27299,
        "female": 26197
    },
    {
        "county": "高雄市",
        "city": "湖內區",
        "households": 9768,
        "population": 28817,
        "male": 14826,
        "female": 13991
    },
    {
        "county": "高雄市",
        "city": "茄萣區",
        "households": 10184,
        "population": 31011,
        "male": 16136,
        "female": 14875
    },
    {
        "county": "高雄市",
        "city": "永安區",
        "households": 5812,
        "population": 14119,
        "male": 7183,
        "female": 6936
    },
    {
        "county": "高雄市",
        "city": "彌陀區",
        "households": 6672,
        "population": 20227,
        "male": 10502,
        "female": 9725
    },
    {
        "county": "高雄市",
        "city": "梓官區",
        "households": 12143,
        "population": 36602,
        "male": 19003,
        "female": 17599
    },
    {
        "county": "高雄市",
        "city": "旗山區",
        "households": 13862,
        "population": 39471,
        "male": 20534,
        "female": 18937
    },
    {
        "county": "高雄市",
        "city": "美濃區",
        "households": 14310,
        "population": 42686,
        "male": 22307,
        "female": 20379
    },
    {
        "county": "高雄市",
        "city": "六龜區",
        "households": 5753,
        "population": 14447,
        "male": 7813,
        "female": 6634
    },
    {
        "county": "高雄市",
        "city": "甲仙區",
        "households": 2494,
        "population": 6999,
        "male": 3752,
        "female": 3247
    },
    {
        "county": "高雄市",
        "city": "杉林區",
        "households": 4587,
        "population": 12120,
        "male": 6613,
        "female": 5507
    },
    {
        "county": "高雄市",
        "city": "內門區",
        "households": 5051,
        "population": 15679,
        "male": 8554,
        "female": 7125
    },
    {
        "county": "高雄市",
        "city": "茂林區",
        "households": 575,
        "population": 1831,
        "male": 919,
        "female": 912
    },
    {
        "county": "高雄市",
        "city": "桃源區",
        "households": 1365,
        "population": 4712,
        "male": 2484,
        "female": 2228
    },
    {
        "county": "高雄市",
        "city": "那瑪夏區",
        "households": 883,
        "population": 3264,
        "male": 1691,
        "female": 1573
    },
    {
        "county": "宜蘭縣",
        "city": "宜蘭市",
        "households": 33634,
        "population": 95614,
        "male": 46960,
        "female": 48654
    },
    {
        "county": "宜蘭縣",
        "city": "羅東鎮",
        "households": 25225,
        "population": 72843,
        "male": 34911,
        "female": 37932
    },
    {
        "county": "宜蘭縣",
        "city": "蘇澳鎮",
        "households": 13699,
        "population": 42440,
        "male": 21744,
        "female": 20696
    },
    {
        "county": "宜蘭縣",
        "city": "頭城鎮",
        "households": 9825,
        "population": 30570,
        "male": 15789,
        "female": 14781
    },
    {
        "county": "宜蘭縣",
        "city": "礁溪鄉",
        "households": 12573,
        "population": 35953,
        "male": 18810,
        "female": 17143
    },
    {
        "county": "宜蘭縣",
        "city": "壯圍鄉",
        "households": 8183,
        "population": 24703,
        "male": 13049,
        "female": 11654
    },
    {
        "county": "宜蘭縣",
        "city": "員山鄉",
        "households": 10934,
        "population": 32272,
        "male": 17288,
        "female": 14984
    },
    {
        "county": "宜蘭縣",
        "city": "冬山鄉",
        "households": 17725,
        "population": 52942,
        "male": 27216,
        "female": 25726
    },
    {
        "county": "宜蘭縣",
        "city": "五結鄉",
        "households": 13211,
        "population": 38804,
        "male": 20146,
        "female": 18658
    },
    {
        "county": "宜蘭縣",
        "city": "三星鄉",
        "households": 7622,
        "population": 21213,
        "male": 11470,
        "female": 9743
    },
    {
        "county": "宜蘭縣",
        "city": "大同鄉",
        "households": 1825,
        "population": 5938,
        "male": 3234,
        "female": 2704
    },
    {
        "county": "宜蘭縣",
        "city": "南澳鄉",
        "households": 1834,
        "population": 5935,
        "male": 3155,
        "female": 2780
    },
    {
        "county": "桃園縣",
        "city": "桃園市",
        "households": 146900,
        "population": 409796,
        "male": 200581,
        "female": 209215
    },
    {
        "county": "桃園縣",
        "city": "中壢市",
        "households": 129820,
        "population": 372117,
        "male": 185570,
        "female": 186547
    },
    {
        "county": "桃園縣",
        "city": "平鎮市",
        "households": 68017,
        "population": 208548,
        "male": 104925,
        "female": 103623
    },
    {
        "county": "桃園縣",
        "city": "八德市",
        "households": 59186,
        "population": 177313,
        "male": 89983,
        "female": 87330
    },
    {
        "county": "桃園縣",
        "city": "楊梅市",
        "households": 49987,
        "population": 152345,
        "male": 77414,
        "female": 74931
    },
    {
        "county": "桃園縣",
        "city": "大溪鎮",
        "households": 29577,
        "population": 91956,
        "male": 47408,
        "female": 44548
    },
    {
        "county": "桃園縣",
        "city": "蘆竹鄉",
        "households": 49388,
        "population": 143770,
        "male": 72007,
        "female": 71763
    },
    {
        "county": "桃園縣",
        "city": "大園鄉",
        "households": 26436,
        "population": 82076,
        "male": 42557,
        "female": 39519
    },
    {
        "county": "桃園縣",
        "city": "龜山鄉",
        "households": 50911,
        "population": 138314,
        "male": 69946,
        "female": 68368
    },
    {
        "county": "桃園縣",
        "city": "龍潭鄉",
        "households": 37343,
        "population": 114974,
        "male": 58359,
        "female": 56615
    },
    {
        "county": "桃園縣",
        "city": "新屋鄉",
        "households": 15046,
        "population": 48661,
        "male": 26064,
        "female": 22597
    },
    {
        "county": "桃園縣",
        "city": "觀音鄉",
        "households": 19580,
        "population": 61646,
        "male": 32462,
        "female": 29184
    },
    {
        "county": "桃園縣",
        "city": "復興鄉",
        "households": 3690,
        "population": 10658,
        "male": 5947,
        "female": 4711
    },
    {
        "county": "新竹縣",
        "city": "竹北市",
        "households": 49376,
        "population": 146510,
        "male": 73298,
        "female": 73212
    },
    {
        "county": "新竹縣",
        "city": "關西鎮",
        "households": 9323,
        "population": 31584,
        "male": 16821,
        "female": 14763
    },
    {
        "county": "新竹縣",
        "city": "新埔鎮",
        "households": 10473,
        "population": 35248,
        "male": 18677,
        "female": 16571
    },
    {
        "county": "新竹縣",
        "city": "竹東鎮",
        "households": 31093,
        "population": 96462,
        "male": 48595,
        "female": 47867
    },
    {
        "county": "新竹縣",
        "city": "湖口鄉",
        "households": 23776,
        "population": 75891,
        "male": 38703,
        "female": 37188
    },
    {
        "county": "新竹縣",
        "city": "橫山鄉",
        "households": 4457,
        "population": 14200,
        "male": 7680,
        "female": 6520
    },
    {
        "county": "新竹縣",
        "city": "新豐鄉",
        "households": 16088,
        "population": 53593,
        "male": 27580,
        "female": 26013
    },
    {
        "county": "新竹縣",
        "city": "芎林鄉",
        "households": 6323,
        "population": 20525,
        "male": 10817,
        "female": 9708
    },
    {
        "county": "新竹縣",
        "city": "寶山鄉",
        "households": 4808,
        "population": 14088,
        "male": 7620,
        "female": 6468
    },
    {
        "county": "新竹縣",
        "city": "北埔鄉",
        "households": 3116,
        "population": 10003,
        "male": 5447,
        "female": 4556
    },
    {
        "county": "新竹縣",
        "city": "峨眉鄉",
        "households": 2038,
        "population": 5916,
        "male": 3270,
        "female": 2646
    },
    {
        "county": "新竹縣",
        "city": "尖石鄉",
        "households": 2723,
        "population": 8660,
        "male": 4703,
        "female": 3957
    },
    {
        "county": "新竹縣",
        "city": "五峰鄉",
        "households": 1733,
        "population": 4629,
        "male": 2537,
        "female": 2092
    },
    {
        "county": "苗栗縣",
        "city": "苗栗市",
        "households": 29506,
        "population": 90814,
        "male": 45664,
        "female": 45150
    },
    {
        "county": "苗栗縣",
        "city": "苑裡鎮",
        "households": 13969,
        "population": 48485,
        "male": 25309,
        "female": 23176
    },
    {
        "county": "苗栗縣",
        "city": "通霄鎮",
        "households": 11411,
        "population": 37644,
        "male": 19898,
        "female": 17746
    },
    {
        "county": "苗栗縣",
        "city": "竹南鎮",
        "households": 24782,
        "population": 79572,
        "male": 40404,
        "female": 39168
    },
    {
        "county": "苗栗縣",
        "city": "頭份鎮",
        "households": 30400,
        "population": 98303,
        "male": 49867,
        "female": 48436
    },
    {
        "county": "苗栗縣",
        "city": "後龍鎮",
        "households": 11789,
        "population": 39013,
        "male": 20622,
        "female": 18391
    },
    {
        "county": "苗栗縣",
        "city": "卓蘭鎮",
        "households": 5994,
        "population": 18404,
        "male": 9702,
        "female": 8702
    },
    {
        "county": "苗栗縣",
        "city": "大湖鄉",
        "households": 5354,
        "population": 15922,
        "male": 8464,
        "female": 7458
    },
    {
        "county": "苗栗縣",
        "city": "公館鄉",
        "households": 10319,
        "population": 34848,
        "male": 18224,
        "female": 16624
    },
    {
        "county": "苗栗縣",
        "city": "銅鑼鄉",
        "households": 6007,
        "population": 19346,
        "male": 10263,
        "female": 9083
    },
    {
        "county": "苗栗縣",
        "city": "南庄鄉",
        "households": 4004,
        "population": 11026,
        "male": 6074,
        "female": 4952
    },
    {
        "county": "苗栗縣",
        "city": "頭屋鄉",
        "households": 3548,
        "population": 11525,
        "male": 6079,
        "female": 5446
    },
    {
        "county": "苗栗縣",
        "city": "三義鄉",
        "households": 5330,
        "population": 17478,
        "male": 9210,
        "female": 8268
    },
    {
        "county": "苗栗縣",
        "city": "西湖鄉",
        "households": 2686,
        "population": 7811,
        "male": 4332,
        "female": 3479
    },
    {
        "county": "苗栗縣",
        "city": "造橋鄉",
        "households": 4053,
        "population": 13683,
        "male": 7215,
        "female": 6468
    },
    {
        "county": "苗栗縣",
        "city": "三灣鄉",
        "households": 2398,
        "population": 7193,
        "male": 3917,
        "female": 3276
    },
    {
        "county": "苗栗縣",
        "city": "獅潭鄉",
        "households": 1687,
        "population": 4831,
        "male": 2705,
        "female": 2126
    },
    {
        "county": "苗栗縣",
        "city": "泰安鄉",
        "households": 1949,
        "population": 5935,
        "male": 3225,
        "female": 2710
    },
    {
        "county": "彰化縣",
        "city": "彰化市",
        "households": 72786,
        "population": 236571,
        "male": 117648,
        "female": 118923
    },
    {
        "county": "彰化縣",
        "city": "鹿港鎮",
        "households": 22644,
        "population": 85416,
        "male": 43761,
        "female": 41655
    },
    {
        "county": "彰化縣",
        "city": "和美鎮",
        "households": 24624,
        "population": 90168,
        "male": 46143,
        "female": 44025
    },
    {
        "county": "彰化縣",
        "city": "北斗鎮",
        "households": 10060,
        "population": 33372,
        "male": 16911,
        "female": 16461
    },
    {
        "county": "彰化縣",
        "city": "員林鎮",
        "households": 37141,
        "population": 125083,
        "male": 62848,
        "female": 62235
    },
    {
        "county": "彰化縣",
        "city": "溪湖鎮",
        "households": 15314,
        "population": 55896,
        "male": 28524,
        "female": 27372
    },
    {
        "county": "彰化縣",
        "city": "田中鎮",
        "households": 12613,
        "population": 43688,
        "male": 22702,
        "female": 20986
    },
    {
        "county": "彰化縣",
        "city": "二林鎮",
        "households": 14426,
        "population": 53562,
        "male": 27668,
        "female": 25894
    },
    {
        "county": "彰化縣",
        "city": "線西鄉",
        "households": 4156,
        "population": 17009,
        "male": 8767,
        "female": 8242
    },
    {
        "county": "彰化縣",
        "city": "伸港鄉",
        "households": 9097,
        "population": 35950,
        "male": 18446,
        "female": 17504
    },
    {
        "county": "彰化縣",
        "city": "福興鄉",
        "households": 12205,
        "population": 48634,
        "male": 25385,
        "female": 23249
    },
    {
        "county": "彰化縣",
        "city": "秀水鄉",
        "households": 9916,
        "population": 39237,
        "male": 20299,
        "female": 18938
    },
    {
        "county": "彰化縣",
        "city": "花壇鄉",
        "households": 13138,
        "population": 46026,
        "male": 23674,
        "female": 22352
    },
    {
        "county": "彰化縣",
        "city": "芬園鄉",
        "households": 6876,
        "population": 24665,
        "male": 13087,
        "female": 11578
    },
    {
        "county": "彰化縣",
        "city": "大村鄉",
        "households": 10379,
        "population": 36549,
        "male": 19059,
        "female": 17490
    },
    {
        "county": "彰化縣",
        "city": "埔鹽鄉",
        "households": 8889,
        "population": 34112,
        "male": 17863,
        "female": 16249
    },
    {
        "county": "彰化縣",
        "city": "埔心鄉",
        "households": 10058,
        "population": 35295,
        "male": 18220,
        "female": 17075
    },
    {
        "county": "彰化縣",
        "city": "永靖鄉",
        "households": 10482,
        "population": 38930,
        "male": 20218,
        "female": 18712
    },
    {
        "county": "彰化縣",
        "city": "社頭鄉",
        "households": 12389,
        "population": 44454,
        "male": 22810,
        "female": 21644
    },
    {
        "county": "彰化縣",
        "city": "二水鄉",
        "households": 5337,
        "population": 16368,
        "male": 8601,
        "female": 7767
    },
    {
        "county": "彰化縣",
        "city": "田尾鄉",
        "households": 7713,
        "population": 28396,
        "male": 14787,
        "female": 13609
    },
    {
        "county": "彰化縣",
        "city": "埤頭鄉",
        "households": 8679,
        "population": 31506,
        "male": 16425,
        "female": 15081
    },
    {
        "county": "彰化縣",
        "city": "芳苑鄉",
        "households": 10018,
        "population": 35785,
        "male": 18925,
        "female": 16860
    },
    {
        "county": "彰化縣",
        "city": "大城鄉",
        "households": 5396,
        "population": 18667,
        "male": 10129,
        "female": 8538
    },
    {
        "county": "彰化縣",
        "city": "竹塘鄉",
        "households": 4607,
        "population": 16377,
        "male": 8608,
        "female": 7769
    },
    {
        "county": "彰化縣",
        "city": "溪州鄉",
        "households": 8726,
        "population": 31346,
        "male": 16498,
        "female": 14848
    },
    {
        "county": "南投縣",
        "city": "南投市",
        "households": 33593,
        "population": 103697,
        "male": 52145,
        "female": 51552
    },
    {
        "county": "南投縣",
        "city": "埔里鎮",
        "households": 28500,
        "population": 84628,
        "male": 42690,
        "female": 41938
    },
    {
        "county": "南投縣",
        "city": "草屯鎮",
        "households": 31302,
        "population": 99225,
        "male": 50154,
        "female": 49071
    },
    {
        "county": "南投縣",
        "city": "竹山鎮",
        "households": 19344,
        "population": 58007,
        "male": 29902,
        "female": 28105
    },
    {
        "county": "南投縣",
        "city": "集集鎮",
        "households": 4306,
        "population": 11750,
        "male": 6144,
        "female": 5606
    },
    {
        "county": "南投縣",
        "city": "名間鄉",
        "households": 12216,
        "population": 40973,
        "male": 21511,
        "female": 19462
    },
    {
        "county": "南投縣",
        "city": "鹿谷鄉",
        "households": 6931,
        "population": 18964,
        "male": 10066,
        "female": 8898
    },
    {
        "county": "南投縣",
        "city": "中寮鄉",
        "households": 5644,
        "population": 16018,
        "male": 8707,
        "female": 7311
    },
    {
        "county": "南投縣",
        "city": "魚池鄉",
        "households": 5739,
        "population": 16941,
        "male": 8938,
        "female": 8003
    },
    {
        "county": "南投縣",
        "city": "國姓鄉",
        "households": 7214,
        "population": 20373,
        "male": 11101,
        "female": 9272
    },
    {
        "county": "南投縣",
        "city": "水里鄉",
        "households": 7224,
        "population": 19724,
        "male": 10332,
        "female": 9392
    },
    {
        "county": "南投縣",
        "city": "信義鄉",
        "households": 5262,
        "population": 17086,
        "male": 9252,
        "female": 7834
    },
    {
        "county": "南投縣",
        "city": "仁愛鄉",
        "households": 4919,
        "population": 15577,
        "male": 8131,
        "female": 7446
    },
    {
        "county": "雲林縣",
        "city": "斗六市",
        "households": 35297,
        "population": 107094,
        "male": 53790,
        "female": 53304
    },
    {
        "county": "雲林縣",
        "city": "斗南鎮",
        "households": 15370,
        "population": 46839,
        "male": 23825,
        "female": 23014
    },
    {
        "county": "雲林縣",
        "city": "虎尾鎮",
        "households": 22833,
        "population": 70076,
        "male": 35635,
        "female": 34441
    },
    {
        "county": "雲林縣",
        "city": "西螺鎮",
        "households": 14127,
        "population": 48113,
        "male": 24513,
        "female": 23600
    },
    {
        "county": "雲林縣",
        "city": "土庫鎮",
        "households": 8853,
        "population": 30257,
        "male": 15814,
        "female": 14443
    },
    {
        "county": "雲林縣",
        "city": "北港鎮",
        "households": 15500,
        "population": 42535,
        "male": 22135,
        "female": 20400
    },
    {
        "county": "雲林縣",
        "city": "古坑鄉",
        "households": 10695,
        "population": 33685,
        "male": 17797,
        "female": 15888
    },
    {
        "county": "雲林縣",
        "city": "大埤鄉",
        "households": 6670,
        "population": 20889,
        "male": 11209,
        "female": 9680
    },
    {
        "county": "雲林縣",
        "city": "莿桐鄉",
        "households": 9094,
        "population": 30270,
        "male": 15889,
        "female": 14381
    },
    {
        "county": "雲林縣",
        "city": "林內鄉",
        "households": 5786,
        "population": 19625,
        "male": 10229,
        "female": 9396
    },
    {
        "county": "雲林縣",
        "city": "二崙鄉",
        "households": 8746,
        "population": 29346,
        "male": 15728,
        "female": 13618
    },
    {
        "county": "雲林縣",
        "city": "崙背鄉",
        "households": 8336,
        "population": 26905,
        "male": 14177,
        "female": 12728
    },
    {
        "county": "雲林縣",
        "city": "麥寮鄉",
        "households": 12877,
        "population": 39049,
        "male": 20223,
        "female": 18826
    },
    {
        "county": "雲林縣",
        "city": "東勢鄉",
        "households": 5726,
        "population": 16398,
        "male": 8937,
        "female": 7461
    },
    {
        "county": "雲林縣",
        "city": "褒忠鄉",
        "households": 4299,
        "population": 14021,
        "male": 7488,
        "female": 6533
    },
    {
        "county": "雲林縣",
        "city": "臺西鄉",
        "households": 8900,
        "population": 25704,
        "male": 13834,
        "female": 11870
    },
    {
        "county": "雲林縣",
        "city": "元長鄉",
        "households": 9354,
        "population": 28406,
        "male": 15490,
        "female": 12916
    },
    {
        "county": "雲林縣",
        "city": "四湖鄉",
        "households": 9056,
        "population": 26338,
        "male": 14341,
        "female": 11997
    },
    {
        "county": "雲林縣",
        "city": "口湖鄉",
        "households": 9600,
        "population": 29902,
        "male": 15932,
        "female": 13970
    },
    {
        "county": "雲林縣",
        "city": "水林鄉",
        "households": 10347,
        "population": 28304,
        "male": 15501,
        "female": 12803
    },
    {
        "county": "嘉義縣",
        "city": "太保市",
        "households": 11527,
        "population": 36687,
        "male": 18899,
        "female": 17788
    },
    {
        "county": "嘉義縣",
        "city": "朴子市",
        "households": 14842,
        "population": 43910,
        "male": 22339,
        "female": 21571
    },
    {
        "county": "嘉義縣",
        "city": "布袋鎮",
        "households": 10158,
        "population": 29693,
        "male": 15224,
        "female": 14469
    },
    {
        "county": "嘉義縣",
        "city": "大林鎮",
        "households": 11267,
        "population": 33219,
        "male": 17064,
        "female": 16155
    },
    {
        "county": "嘉義縣",
        "city": "民雄鄉",
        "households": 23120,
        "population": 72444,
        "male": 37176,
        "female": 35268
    },
    {
        "county": "嘉義縣",
        "city": "溪口鄉",
        "households": 5391,
        "population": 16038,
        "male": 8568,
        "female": 7470
    },
    {
        "county": "嘉義縣",
        "city": "新港鄉",
        "households": 10433,
        "population": 34254,
        "male": 18069,
        "female": 16185
    },
    {
        "county": "嘉義縣",
        "city": "六腳鄉",
        "households": 9143,
        "population": 25923,
        "male": 13735,
        "female": 12188
    },
    {
        "county": "嘉義縣",
        "city": "東石鄉",
        "households": 9503,
        "population": 27234,
        "male": 14476,
        "female": 12758
    },
    {
        "county": "嘉義縣",
        "city": "義竹鄉",
        "households": 7474,
        "population": 20664,
        "male": 10731,
        "female": 9933
    },
    {
        "county": "嘉義縣",
        "city": "鹿草鄉",
        "households": 5796,
        "population": 17037,
        "male": 9169,
        "female": 7868
    },
    {
        "county": "嘉義縣",
        "city": "水上鄉",
        "households": 17454,
        "population": 51809,
        "male": 26728,
        "female": 25081
    },
    {
        "county": "嘉義縣",
        "city": "中埔鄉",
        "households": 15529,
        "population": 47278,
        "male": 24655,
        "female": 22623
    },
    {
        "county": "嘉義縣",
        "city": "竹崎鄉",
        "households": 11433,
        "population": 38227,
        "male": 20376,
        "female": 17851
    },
    {
        "county": "嘉義縣",
        "city": "梅山鄉",
        "households": 6678,
        "population": 21216,
        "male": 11230,
        "female": 9986
    },
    {
        "county": "嘉義縣",
        "city": "番路鄉",
        "households": 4066,
        "population": 11844,
        "male": 6453,
        "female": 5391
    },
    {
        "county": "嘉義縣",
        "city": "大埔鄉",
        "households": 1930,
        "population": 4551,
        "male": 2396,
        "female": 2155
    },
    {
        "county": "嘉義縣",
        "city": "阿里山鄉",
        "households": 2071,
        "population": 6181,
        "male": 3297,
        "female": 2884
    },
    {
        "county": "屏東縣",
        "city": "屏東市",
        "households": 72423,
        "population": 209446,
        "male": 104335,
        "female": 105111
    },
    {
        "county": "屏東縣",
        "city": "潮州鎮",
        "households": 18352,
        "population": 55336,
        "male": 27805,
        "female": 27531
    },
    {
        "county": "屏東縣",
        "city": "東港鎮",
        "households": 15830,
        "population": 49585,
        "male": 25074,
        "female": 24511
    },
    {
        "county": "屏東縣",
        "city": "恆春鎮",
        "households": 10887,
        "population": 30863,
        "male": 15809,
        "female": 15054
    },
    {
        "county": "屏東縣",
        "city": "萬丹鄉",
        "households": 14411,
        "population": 53540,
        "male": 27712,
        "female": 25828
    },
    {
        "county": "屏東縣",
        "city": "長治鄉",
        "households": 9785,
        "population": 30688,
        "male": 16044,
        "female": 14644
    },
    {
        "county": "屏東縣",
        "city": "麟洛鄉",
        "households": 3614,
        "population": 11425,
        "male": 5917,
        "female": 5508
    },
    {
        "county": "屏東縣",
        "city": "九如鄉",
        "households": 6618,
        "population": 22729,
        "male": 11810,
        "female": 10919
    },
    {
        "county": "屏東縣",
        "city": "里港鄉",
        "households": 7913,
        "population": 25769,
        "male": 13193,
        "female": 12576
    },
    {
        "county": "屏東縣",
        "city": "鹽埔鄉",
        "households": 7763,
        "population": 27042,
        "male": 14054,
        "female": 12988
    },
    {
        "county": "屏東縣",
        "city": "高樹鄉",
        "households": 9419,
        "population": 26359,
        "male": 14064,
        "female": 12295
    },
    {
        "county": "屏東縣",
        "city": "萬巒鄉",
        "households": 6435,
        "population": 21635,
        "male": 11398,
        "female": 10237
    },
    {
        "county": "屏東縣",
        "city": "內埔鄉",
        "households": 17987,
        "population": 57572,
        "male": 29903,
        "female": 27669
    },
    {
        "county": "屏東縣",
        "city": "竹田鄉",
        "households": 5590,
        "population": 18190,
        "male": 9647,
        "female": 8543
    },
    {
        "county": "屏東縣",
        "city": "新埤鄉",
        "households": 3374,
        "population": 10558,
        "male": 5606,
        "female": 4952
    },
    {
        "county": "屏東縣",
        "city": "枋寮鄉",
        "households": 8502,
        "population": 26253,
        "male": 13794,
        "female": 12459
    },
    {
        "county": "屏東縣",
        "city": "新園鄉",
        "households": 11601,
        "population": 37841,
        "male": 19570,
        "female": 18271
    },
    {
        "county": "屏東縣",
        "city": "崁頂鄉",
        "households": 4300,
        "population": 17043,
        "male": 8692,
        "female": 8351
    },
    {
        "county": "屏東縣",
        "city": "林邊鄉",
        "households": 7144,
        "population": 20329,
        "male": 10474,
        "female": 9855
    },
    {
        "county": "屏東縣",
        "city": "南州鄉",
        "households": 3680,
        "population": 11542,
        "male": 5911,
        "female": 5631
    },
    {
        "county": "屏東縣",
        "city": "佳冬鄉",
        "households": 7136,
        "population": 21053,
        "male": 10977,
        "female": 10076
    },
    {
        "county": "屏東縣",
        "city": "琉球鄉",
        "households": 4015,
        "population": 12162,
        "male": 6756,
        "female": 5406
    },
    {
        "county": "屏東縣",
        "city": "車城鄉",
        "households": 3504,
        "population": 9429,
        "male": 5092,
        "female": 4337
    },
    {
        "county": "屏東縣",
        "city": "滿州鄉",
        "households": 3049,
        "population": 8256,
        "male": 4558,
        "female": 3698
    },
    {
        "county": "屏東縣",
        "city": "枋山鄉",
        "households": 2103,
        "population": 5925,
        "male": 3187,
        "female": 2738
    },
    {
        "county": "屏東縣",
        "city": "三地門鄉",
        "households": 2224,
        "population": 7545,
        "male": 3851,
        "female": 3694
    },
    {
        "county": "屏東縣",
        "city": "霧臺鄉",
        "households": 993,
        "population": 2962,
        "male": 1557,
        "female": 1405
    },
    {
        "county": "屏東縣",
        "city": "瑪家鄉",
        "households": 1929,
        "population": 6550,
        "male": 3406,
        "female": 3144
    },
    {
        "county": "屏東縣",
        "city": "泰武鄉",
        "households": 1241,
        "population": 5079,
        "male": 2654,
        "female": 2425
    },
    {
        "county": "屏東縣",
        "city": "來義鄉",
        "households": 2186,
        "population": 7690,
        "male": 3943,
        "female": 3747
    },
    {
        "county": "屏東縣",
        "city": "春日鄉",
        "households": 1327,
        "population": 4847,
        "male": 2512,
        "female": 2335
    },
    {
        "county": "屏東縣",
        "city": "獅子鄉",
        "households": 1466,
        "population": 4814,
        "male": 2544,
        "female": 2270
    },
    {
        "county": "屏東縣",
        "city": "牡丹鄉",
        "households": 1884,
        "population": 4922,
        "male": 2554,
        "female": 2368
    },
    {
        "county": "臺東縣",
        "city": "臺東市",
        "households": 38254,
        "population": 108331,
        "male": 54818,
        "female": 53513
    },
    {
        "county": "臺東縣",
        "city": "成功鎮",
        "households": 5425,
        "population": 15572,
        "male": 8257,
        "female": 7315
    },
    {
        "county": "臺東縣",
        "city": "關山鎮",
        "households": 3223,
        "population": 9564,
        "male": 5021,
        "female": 4543
    },
    {
        "county": "臺東縣",
        "city": "卑南鄉",
        "households": 6629,
        "population": 18069,
        "male": 9724,
        "female": 8345
    },
    {
        "county": "臺東縣",
        "city": "大武鄉",
        "households": 2520,
        "population": 6803,
        "male": 3565,
        "female": 3238
    },
    {
        "county": "臺東縣",
        "city": "太麻里鄉",
        "households": 4533,
        "population": 11834,
        "male": 6314,
        "female": 5520
    },
    {
        "county": "臺東縣",
        "city": "東河鄉",
        "households": 3624,
        "population": 9234,
        "male": 5145,
        "female": 4089
    },
    {
        "county": "臺東縣",
        "city": "長濱鄉",
        "households": 2937,
        "population": 8061,
        "male": 4601,
        "female": 3460
    },
    {
        "county": "臺東縣",
        "city": "鹿野鄉",
        "households": 3126,
        "population": 8414,
        "male": 4538,
        "female": 3876
    },
    {
        "county": "臺東縣",
        "city": "池上鄉",
        "households": 3258,
        "population": 9020,
        "male": 4762,
        "female": 4258
    },
    {
        "county": "臺東縣",
        "city": "綠島鄉",
        "households": 1035,
        "population": 3411,
        "male": 1808,
        "female": 1603
    },
    {
        "county": "臺東縣",
        "city": "延平鄉",
        "households": 1063,
        "population": 3556,
        "male": 1958,
        "female": 1598
    },
    {
        "county": "臺東縣",
        "city": "海端鄉",
        "households": 1099,
        "population": 4411,
        "male": 2398,
        "female": 2013
    },
    {
        "county": "臺東縣",
        "city": "達仁鄉",
        "households": 1505,
        "population": 3957,
        "male": 2163,
        "female": 1794
    },
    {
        "county": "臺東縣",
        "city": "金峰鄉",
        "households": 1061,
        "population": 3517,
        "male": 1827,
        "female": 1690
    },
    {
        "county": "臺東縣",
        "city": "蘭嶼鄉",
        "households": 1528,
        "population": 4676,
        "male": 2404,
        "female": 2272
    },
    {
        "county": "花蓮縣",
        "city": "花蓮市",
        "households": 40772,
        "population": 108699,
        "male": 53212,
        "female": 55487
    },
    {
        "county": "花蓮縣",
        "city": "鳳林鎮",
        "households": 4425,
        "population": 11732,
        "male": 6193,
        "female": 5539
    },
    {
        "county": "花蓮縣",
        "city": "玉里鎮",
        "households": 8894,
        "population": 26471,
        "male": 14312,
        "female": 12159
    },
    {
        "county": "花蓮縣",
        "city": "新城鄉",
        "households": 7344,
        "population": 20116,
        "male": 10448,
        "female": 9668
    },
    {
        "county": "花蓮縣",
        "city": "吉安鄉",
        "households": 29551,
        "population": 80442,
        "male": 41042,
        "female": 39400
    },
    {
        "county": "花蓮縣",
        "city": "壽豐鄉",
        "households": 6846,
        "population": 18496,
        "male": 9990,
        "female": 8506
    },
    {
        "county": "花蓮縣",
        "city": "光復鄉",
        "households": 5051,
        "population": 13852,
        "male": 7390,
        "female": 6462
    },
    {
        "county": "花蓮縣",
        "city": "豐濱鄉",
        "households": 1789,
        "population": 4880,
        "male": 2710,
        "female": 2170
    },
    {
        "county": "花蓮縣",
        "city": "瑞穗鄉",
        "households": 4639,
        "population": 12608,
        "male": 6816,
        "female": 5792
    },
    {
        "county": "花蓮縣",
        "city": "富里鄉",
        "households": 4009,
        "population": 11406,
        "male": 6211,
        "female": 5195
    },
    {
        "county": "花蓮縣",
        "city": "秀林鄉",
        "households": 4683,
        "population": 15166,
        "male": 7872,
        "female": 7294
    },
    {
        "county": "花蓮縣",
        "city": "萬榮鄉",
        "households": 2124,
        "population": 6740,
        "male": 3605,
        "female": 3135
    },
    {
        "county": "花蓮縣",
        "city": "卓溪鄉",
        "households": 1659,
        "population": 6228,
        "male": 3467,
        "female": 2761
    },
    {
        "county": "澎湖縣",
        "city": "馬公市",
        "households": 20933,
        "population": 57378,
        "male": 29044,
        "female": 28334
    },
    {
        "county": "澎湖縣",
        "city": "湖西鄉",
        "households": 4855,
        "population": 13712,
        "male": 7151,
        "female": 6561
    },
    {
        "county": "澎湖縣",
        "city": "白沙鄉",
        "households": 3174,
        "population": 9401,
        "male": 4930,
        "female": 4471
    },
    {
        "county": "澎湖縣",
        "city": "西嶼鄉",
        "households": 2862,
        "population": 8363,
        "male": 4309,
        "female": 4054
    },
    {
        "county": "澎湖縣",
        "city": "望安鄉",
        "households": 1899,
        "population": 4660,
        "male": 2519,
        "female": 2141
    },
    {
        "county": "澎湖縣",
        "city": "七美鄉",
        "households": 1267,
        "population": 3577,
        "male": 1872,
        "female": 1705
    },
    {
        "county": "基隆市",
        "city": "中正區",
        "households": 22157,
        "population": 54520,
        "male": 27926,
        "female": 26594
    },
    {
        "county": "基隆市",
        "city": "七堵區",
        "households": 20281,
        "population": 54772,
        "male": 27757,
        "female": 27015
    },
    {
        "county": "基隆市",
        "city": "暖暖區",
        "households": 14581,
        "population": 37958,
        "male": 19245,
        "female": 18713
    },
    {
        "county": "基隆市",
        "city": "仁愛區",
        "households": 19808,
        "population": 48752,
        "male": 24056,
        "female": 24696
    },
    {
        "county": "基隆市",
        "city": "中山區",
        "households": 19209,
        "population": 50379,
        "male": 25738,
        "female": 24641
    },
    {
        "county": "基隆市",
        "city": "安樂區",
        "households": 31785,
        "population": 82898,
        "male": 41342,
        "female": 41556
    },
    {
        "county": "基隆市",
        "city": "信義區",
        "households": 20211,
        "population": 51002,
        "male": 25509,
        "female": 25493
    },
    {
        "county": "新竹市",
        "city": "東區",
        "households": 70141,
        "population": 199557,
        "male": 98514,
        "female": 101043
    },
    {
        "county": "新竹市",
        "city": "北區",
        "households": 51588,
        "population": 146189,
        "male": 72082,
        "female": 74107
    },
    {
        "county": "新竹市",
        "city": "香山區",
        "households": 23596,
        "population": 73638,
        "male": 37551,
        "female": 36087
    },
    {
        "county": "嘉義市",
        "city": "東區",
        "households": 44373,
        "population": 124560,
        "male": 60811,
        "female": 63749
    },
    {
        "county": "嘉義市",
        "city": "西區",
        "households": 51638,
        "population": 147034,
        "male": 72664,
        "female": 74370
    },
    {
        "county": "金門縣",
        "city": "金城鎮",
        "households": 11381,
        "population": 34058,
        "male": 17222,
        "female": 16836
    },
    {
        "county": "金門縣",
        "city": "金湖鎮",
        "households": 7557,
        "population": 22601,
        "male": 11488,
        "female": 11113
    },
    {
        "county": "金門縣",
        "city": "金沙鎮",
        "households": 5533,
        "population": 16238,
        "male": 8176,
        "female": 8062
    },
    {
        "county": "金門縣",
        "city": "金寧鄉",
        "households": 6426,
        "population": 20408,
        "male": 10481,
        "female": 9927
    },
    {
        "county": "金門縣",
        "city": "烈嶼鄉",
        "households": 2715,
        "population": 9470,
        "male": 4705,
        "female": 4765
    },
    {
        "county": "金門縣",
        "city": "烏坵鄉",
        "households": 135,
        "population": 565,
        "male": 281,
        "female": 284
    },
    {
        "county": "連江縣",
        "city": "南竿鄉",
        "households": 1260,
        "population": 6002,
        "male": 3444,
        "female": 2558
    },
    {
        "county": "連江縣",
        "city": "北竿鄉",
        "households": 404,
        "population": 1862,
        "male": 1057,
        "female": 805
    },
    {
        "county": "連江縣",
        "city": "莒光鄉",
        "households": 246,
        "population": 1163,
        "male": 701,
        "female": 462
    },
    {
        "county": "連江縣",
        "city": "東引鄉",
        "households": 278,
        "population": 1077,
        "male": 639,
        "female": 438
    }
]